{
    "User": [
        {
            "name": "Sourabh",
            "email": "ankushgupta41097@gmail.com",
            "password": "1234556",
            "mobile": 8881104454,
            "userId": "4562b7b5-dc19-4366-885b-9fd40a39fe61"
        },
        {
            "email": "ankush_fw14_733@masai.school",
            "password": "123456",
            "mobile": "8881104452",
            "name": "Ankush",
            "userId": "10661b52-82f0-4859-ada2-33dfa0f8fc3d"
        },
        {
            "email": "ankush_fw14_733@masai.school",
            "password": "123456",
            "mobile": "8881104450",
            "name": "Ankush",
            "userId": "6120c1fe-cec1-4707-806c-85328489e988"
        },
        {
            "name": "Ankit",
            "email": "a@a.com",
            "password": "1234556",
            "mobile": 888110447,
            "userId": "888527a5-94da-409c-9257-f78e8844b28a"
        }
    ],
    "Task": [
        {
            "title": "tty",
            "expiry": "8",
            "userId": "4562b7b5-dc19-4366-885b-9fd40a39fe61",
            "startTime": 1657737569301,
            "taskId": "7e054c53-6fbe-47b8-8cfb-61f93ffd4511"
        },
        {
            "title": "something",
            "expiry": "7",
            "userId": "4562b7b5-dc19-4366-885b-9fd40a39fe61",
            "startTime": 1657778636484,
            "taskId": "16fc8f70-0f79-4d62-a674-0b8094d96ace"
        },
        {
            "title": "xyz7856",
            "expiry": "10",
            "userId": "4562b7b5-dc19-4366-885b-9fd40a39fe61",
            "startTime": 1657780391758,
            "taskId": "0ff2d699-4b00-4bcc-84f7-e3eea42fc36b"
        },
        {
            "title": "hello",
            "expiry": "8",
            "userId": "4562b7b5-dc19-4366-885b-9fd40a39fe61",
            "startTime": 1657780455202,
            "taskId": "c087e24a-c1e5-4aff-82e4-dc2555fff048"
        },
        {
            "title": "newtask",
            "expiry": "1",
            "userId": "4562b7b5-dc19-4366-885b-9fd40a39fe61",
            "startTime": 1657780717042,
            "taskId": "2aa8fb0d-f28b-46ee-bfcd-f1ff19d0374c"
        },
        {
            "title": "newtask",
            "expiry": "1",
            "userId": "4562b7b5-dc19-4366-885b-9fd40a39fe61",
            "startTime": 1657780718499,
            "taskId": "d431141a-989c-4e53-9983-3c3220601b75"
        },
        {
            "title": "newtask",
            "expiry": "6",
            "userId": "4562b7b5-dc19-4366-885b-9fd40a39fe61",
            "startTime": 1657780863597,
            "taskId": "a3a8789d-f2fc-4462-a627-5f002402e4f9"
        },
        {
            "title": "dfdg",
            "expiry": "6",
            "userId": "4562b7b5-dc19-4366-885b-9fd40a39fe61",
            "startTime": 1657780903063,
            "taskId": "39d762ba-b00b-4da7-9782-4f47729aa807"
        },
        {
            "title": "dgds",
            "expiry": "4",
            "userId": "4562b7b5-dc19-4366-885b-9fd40a39fe61",
            "startTime": 1657781004343,
            "taskId": "319698a5-b488-47de-bb00-5df1b1ab2ea6"
        },
        {
            "title": "dgsdg",
            "expiry": "9",
            "userId": "4562b7b5-dc19-4366-885b-9fd40a39fe61",
            "startTime": 1657781053122,
            "taskId": "dd5198d2-34e6-4af6-94eb-e337a820fa76"
        },
        {
            "title": "dgsdg",
            "expiry": "9",
            "userId": "4562b7b5-dc19-4366-885b-9fd40a39fe61",
            "startTime": 1657781054295,
            "taskId": "401c26b4-25ff-40c7-b506-923acc7e6b5f"
        },
        {
            "title": "dgsdg",
            "expiry": "9",
            "userId": "4562b7b5-dc19-4366-885b-9fd40a39fe61",
            "startTime": 1657781067204,
            "taskId": "d39cb650-a87a-4615-81fb-6347668f62f7"
        },
        {
            "title": "dgsdg",
            "expiry": "9",
            "userId": "4562b7b5-dc19-4366-885b-9fd40a39fe61",
            "startTime": 1657781068382,
            "taskId": "e97db71a-c870-4bee-bf27-b44cabb943e6"
        },
        {
            "title": "dgsdgdg",
            "expiry": "9",
            "userId": "4562b7b5-dc19-4366-885b-9fd40a39fe61",
            "startTime": 1657781180852,
            "taskId": "32ae913a-ed81-4148-875d-761aa65afc2a"
        },
        {
            "title": "mytodo",
            "expiry": "6",
            "userId": "4562b7b5-dc19-4366-885b-9fd40a39fe61",
            "startTime": 1657783479945,
            "taskId": "4be66aa6-ff16-42a4-885e-ff801f58b3fc"
        },
        {
            "title": "dsfsdf",
            "expiry": "4",
            "userId": "4562b7b5-dc19-4366-885b-9fd40a39fe61",
            "startTime": 1657783523497,
            "taskId": "d12dced9-cba8-4f32-9a3b-1fb4a1d43ebb"
        },
        {
            "title": "fsdf",
            "expiry": "6",
            "userId": "4562b7b5-dc19-4366-885b-9fd40a39fe61",
            "startTime": 1657783547921,
            "taskId": "616ffbaf-fbee-454d-96c3-70c9c9670961"
        },
        {
            "title": "sdgfd",
            "expiry": "5",
            "userId": "4562b7b5-dc19-4366-885b-9fd40a39fe61",
            "startTime": 1657783622784,
            "taskId": "6df1ed47-db61-4973-906d-ebe9926ae90e"
        },
        {
            "title": "dsfggd",
            "expiry": "5",
            "userId": "4562b7b5-dc19-4366-885b-9fd40a39fe61",
            "startTime": 1657783697761,
            "taskId": "3314f5fe-6623-45ff-bafb-e55809bf5ad6"
        },
        {
            "title": "hjkhjl",
            "expiry": "8",
            "userId": "4562b7b5-dc19-4366-885b-9fd40a39fe61",
            "startTime": 1657783791838,
            "taskId": "acbfa413-14a2-4558-b2d0-ca1075b63ff7"
        },
        {
            "title": "dfhhnxc",
            "expiry": "",
            "userId": "4562b7b5-dc19-4366-885b-9fd40a39fe61",
            "startTime": 1657783915937,
            "taskId": "eccd7d58-133b-407d-964c-dae1bb50c638"
        },
        {
            "title": "dhsd",
            "expiry": "4",
            "userId": "4562b7b5-dc19-4366-885b-9fd40a39fe61",
            "startTime": 1657783939813,
            "taskId": "16a6470e-7dce-4c3f-a0b7-4a737475ecca"
        },
        {
            "title": "dsgd",
            "expiry": "5",
            "userId": "4562b7b5-dc19-4366-885b-9fd40a39fe61",
            "startTime": 1657784011407,
            "taskId": "8ec32ebd-897c-4d3e-9bda-f94a792f425d"
        },
        {
            "title": "dsgsdg",
            "expiry": "6",
            "userId": "4562b7b5-dc19-4366-885b-9fd40a39fe61",
            "startTime": 1657784033978,
            "taskId": "dc32aa77-bc0c-4340-a96b-2fe533e2ad9c"
        },
        {
            "title": "etrtb",
            "expiry": "8",
            "userId": "4562b7b5-dc19-4366-885b-9fd40a39fe61",
            "startTime": 1657784181420,
            "taskId": "43c2c1a6-bfcb-4505-8035-623417f02c83"
        },
        {
            "title": "sfdgsdg",
            "expiry": "3",
            "userId": "4562b7b5-dc19-4366-885b-9fd40a39fe61",
            "startTime": 1657784282845,
            "taskId": "10582be3-58a1-417f-b0ac-60ed7b8f376e"
        },
        {
            "title": "mathmat",
            "expiry": "5",
            "userId": "4562b7b5-dc19-4366-885b-9fd40a39fe61",
            "startTime": 1657784719281,
            "taskId": "a5b2e8fc-396b-4710-8fab-c91157c20c1b"
        },
        {
            "title": "newtask match",
            "expiry": "9",
            "userId": "4562b7b5-dc19-4366-885b-9fd40a39fe61",
            "startTime": 1657784851092,
            "taskId": "dfd19174-4e89-4878-90f6-83dc919d355d"
        },
        {
            "title": "loading",
            "expiry": "5",
            "userId": "4562b7b5-dc19-4366-885b-9fd40a39fe61",
            "startTime": 1657785137840,
            "taskId": "3c3e6b02-c67a-4b49-a595-abb219cad5e5"
        },
        {
            "title": "coding ",
            "expiry": "10",
            "userId": "888527a5-94da-409c-9257-f78e8844b28a",
            "startTime": 1658283047704,
            "taskId": "24137b6d-6ed3-466c-af9f-973478e31b0b"
        }
    ]
}